khi/__init__.py
khi/beaches.py
khi/clubs.py
khi/districts.py
khi-0.0.7.dist-info/LICENSE
khi-0.0.7.dist-info/METADATA
khi-0.0.7.dist-info/WHEEL
khi-0.0.7.dist-info/top_level.txt
khi-0.0.7.dist-info/RECORD
