Metadata-Version: 2.1
Name: khi
Version: 0.0.7
Summary: Furnish information about the great Karachi city, Pakistan.
Home-page: https://www.techtum.dev
Author: siphr
Author-email: python@techtum.dev
License: MIT
Platform: UNKNOWN
Classifier: Development Status :: 1 - Planning
Classifier: Intended Audience :: Science/Research
Classifier: License :: OSI Approved :: MIT License
Classifier: Operating System :: OS Independent
License-File: LICENSE
Requires-Dist: BeautifulSoup4
